LICENSE
MANIFEST.in
Readme.md
adbgui.xml
devicefile.xml
setup.py
./DeviceFile.py
./__init__.py
./adbgui.py
FormUI/Builder.py
FormUI/BuilderUtil.py
FormUI/ControlBase.py
FormUI/Form.py
FormUI/FormControl.py
FormUI/FormControlBase.py
FormUI/FormUI.py
FormUI/Frame.py
FormUI/WorkThread.py
FormUI/__init__.py
adbgui.egg-info/PKG-INFO
adbgui.egg-info/SOURCES.txt
adbgui.egg-info/dependency_links.txt
adbgui.egg-info/entry_points.txt
adbgui.egg-info/not-zip-safe
adbgui.egg-info/requires.txt
adbgui.egg-info/top_level.txt