Metadata-Version: 1.0
Name: adbgui
Version: 0.3.1
Summary: An adb Gui tool
Home-page: http://www.en7788.com
Author: zhangfeng.zou
Author-email: jeff.chau@hotmail.com
License: MIT
Keywords: adb GUI Python
Platform: UNKNOWN
